{
  "products": [
    {
      "balance": "$3,340",
      "info": "Paypal Logs( Email + number attached + password )",
      "buy": "$70"
    },
    {
      "balance": "$3,360",
      "info": "Paypal Logs( Email + number attached + password )",
      "buy": "$74"
    },
    {
      "balance": "$3,400",
      "info": "Paypal Logs( Email + number attached + password )",
      "buy": "$85"
    },
    {
      "balance": "$4,000",
      "info": "Paypal Logs( Email + number attached + password )",
      "buy": "$90"
    },
    {
      "balance": "$4,410",
      "info": "Paypal Logs( Email + number attached + password )",
      "buy": "$97"
    },
    {
      "balance": "$4,800",
      "info": "Paypal Logs( Email + number attached + password )",
      "buy": "$110"
    },
    {
      "balance": "$5,300",
      "info": "Paypal Logs( Email + number attached + password )",
      "buy": "$130"
    },
    {
      "balance": "$5,518",
      "info": "Paypal Logs( Email + number attached + password )",
      "buy": "$150"
    },
    {
      "balance": "$5,600",
      "info": "Paypal Logs( Email + number attached + password )",
      "buy": "$160"
    },
    {
      "balance": "$5,800",
      "info": "Paypal Logs( Email + number attached + password )",
      "buy": "$165"
    },
    {
      "balance": "$5,960",
      "info": "Paypal Logs( Email + number attached + password )",
      "buy": "$170"
    },
    {
      "balance": "$6,173",
      "info": "Paypal Logs( Email + number attached + password )",
      "buy": "$190"
    },
    {
      "balance": "$6,847",
      "info": "Paypal Logs( Email + number attached + password )",
      "buy": "$194"
    },
    {
      "balance": "$8,419",
      "info": "Paypal Logs( Email + number attached + password )",
      "buy": "$220"
    },
    {
      "balance": "$8,500",
      "info": "Paypal Logs( Email + number attached + password )",
      "buy": "$230"
    }
  ]
}
